[{"patient_id":"P000201","sex":"Male","age_at_diagnosis":7.0,"age_at_death":null,"vital_status":"Alive","hospital":"NSW Hospital1","enrolment_date":1504224000000},{"patient_id":"P000601","sex":"Female","age_at_diagnosis":14.0,"age_at_death":null,"vital_status":"Alive","hospital":"NSW Hospital1","enrolment_date":1506816000000},{"patient_id":"P000803","sex":"Male","age_at_diagnosis":14.0,"age_at_death":17.0,"vital_status":"Dead","hospital":"NSW Hospital2","enrolment_date":1559347200000},{"patient_id":"P000806","sex":"Female","age_at_diagnosis":8.0,"age_at_death":13.0,"vital_status":"Dead","hospital":"QLD Hospital1","enrolment_date":1509494400000},{"patient_id":"P000808","sex":"Female","age_at_diagnosis":14.0,"age_at_death":null,"vital_status":"Alive","hospital":"SA Hospital1","enrolment_date":1554076800000},{"patient_id":"P001103","sex":"Female","age_at_diagnosis":0.0,"age_at_death":null,"vital_status":"Alive","hospital":"NSW Hospital2","enrolment_date":1543622400000},{"patient_id":"P001502","sex":"Male","age_at_diagnosis":22.0,"age_at_death":24.0,"vital_status":"Dead","hospital":"NSW Hospital3","enrolment_date":1527811200000},{"patient_id":"P001805","sex":"Male","age_at_diagnosis":8.0,"age_at_death":null,"vital_status":"Alive","hospital":"VIC Hospital1","enrolment_date":1559347200000},{"patient_id":"P001905","sex":"Male","age_at_diagnosis":14.0,"age_at_death":15.0,"vital_status":"Dead","hospital":"VIC Hospital1","enrolment_date":1559347200000},{"patient_id":"P002006","sex":"Male","age_at_diagnosis":12.0,"age_at_death":null,"vital_status":"Alive","hospital":"QLD Hospital1","enrolment_date":1527811200000},{"patient_id":"P002102","sex":"Female","age_at_diagnosis":14.0,"age_at_death":15.0,"vital_status":"Dead","hospital":"NSW Hospital3","enrolment_date":1530403200000},{"patient_id":"P002207","sex":"Female","age_at_diagnosis":4.0,"age_at_death":null,"vital_status":"Alive","hospital":"WA Hospital1","enrolment_date":1559347200000},{"patient_id":"P002301","sex":"Male","age_at_diagnosis":13.0,"age_at_death":13.0,"vital_status":"Dead","hospital":"NSW Hospital1","enrolment_date":1525132800000},{"patient_id":"P002307","sex":"Female","age_at_diagnosis":1.0,"age_at_death":1.0,"vital_status":"Dead","hospital":"WA Hospital1","enrolment_date":1561939200000},{"patient_id":"P002601","sex":"Female","age_at_diagnosis":17.0,"age_at_death":18.0,"vital_status":"Dead","hospital":"NSW Hospital1","enrolment_date":1527811200000},{"patient_id":"P002704","sex":"Female","age_at_diagnosis":14.0,"age_at_death":null,"vital_status":"Alive","hospital":"VIC Hospital2","enrolment_date":1548979200000},{"patient_id":"P002805","sex":"Male","age_at_diagnosis":null,"age_at_death":null,"vital_status":"Alive","hospital":"VIC Hospital1","enrolment_date":1575158400000},{"patient_id":"P002902","sex":"Male","age_at_diagnosis":9.0,"age_at_death":null,"vital_status":"Alive","hospital":"NSW Hospital3","enrolment_date":1546300800000},{"patient_id":"P003001","sex":"Male","age_at_diagnosis":6.0,"age_at_death":9.0,"vital_status":"Dead","hospital":"NSW Hospital1","enrolment_date":1530403200000},{"patient_id":"P003307","sex":"Male","age_at_diagnosis":16.0,"age_at_death":null,"vital_status":"Alive","hospital":"WA Hospital1","enrolment_date":1575158400000},{"patient_id":"P003506","sex":"Female","age_at_diagnosis":0.0,"age_at_death":null,"vital_status":"Alive","hospital":"QLD Hospital1","enrolment_date":1548979200000},{"patient_id":"P003607","sex":"Female","age_at_diagnosis":12.0,"age_at_death":null,"vital_status":"Alive","hospital":"WA Hospital1","enrolment_date":1577836800000},{"patient_id":"P003804","sex":"Male","age_at_diagnosis":17.0,"age_at_death":null,"vital_status":"Alive","hospital":"VIC Hospital2","enrolment_date":1554076800000},{"patient_id":"P004301","sex":"Male","age_at_diagnosis":11.0,"age_at_death":13.0,"vital_status":"Dead","hospital":"NSW Hospital1","enrolment_date":1543622400000},{"patient_id":"P004801","sex":"Male","age_at_diagnosis":10.0,"age_at_death":null,"vital_status":"Alive","hospital":"NSW Hospital1","enrolment_date":1548979200000},{"patient_id":"P005001","sex":"Female","age_at_diagnosis":1.0,"age_at_death":null,"vital_status":"Alive","hospital":"NSW Hospital1","enrolment_date":1551398400000},{"patient_id":"P005202","sex":"Male","age_at_diagnosis":6.0,"age_at_death":null,"vital_status":"Alive","hospital":"NSW Hospital3","enrolment_date":1567296000000},{"patient_id":"P005304","sex":"Female","age_at_diagnosis":4.0,"age_at_death":null,"vital_status":"Alive","hospital":"VIC Hospital2","enrolment_date":1569888000000},{"patient_id":"P005404","sex":"Female","age_at_diagnosis":0.0,"age_at_death":null,"vital_status":"Alive","hospital":"VIC Hospital2","enrolment_date":1569888000000},{"patient_id":"P005501","sex":"Male","age_at_diagnosis":14.0,"age_at_death":15.0,"vital_status":"Dead","hospital":"NSW Hospital1","enrolment_date":1554076800000},{"patient_id":"P005602","sex":"Female","age_at_diagnosis":null,"age_at_death":15.0,"vital_status":"Dead","hospital":"NSW Hospital3","enrolment_date":1569888000000},{"patient_id":"P005702","sex":"Male","age_at_diagnosis":10.0,"age_at_death":null,"vital_status":"Alive","hospital":"NSW Hospital3","enrolment_date":1569888000000},{"patient_id":"P005704","sex":"Female","age_at_diagnosis":3.0,"age_at_death":null,"vital_status":"Alive","hospital":"VIC Hospital2","enrolment_date":1572566400000},{"patient_id":"P005801","sex":"Female","age_at_diagnosis":6.0,"age_at_death":6.0,"vital_status":"Dead","hospital":"NSW Hospital1","enrolment_date":1559347200000},{"patient_id":"P005906","sex":"Male","age_at_diagnosis":8.0,"age_at_death":null,"vital_status":"Alive","hospital":"QLD Hospital1","enrolment_date":1585699200000},{"patient_id":"P006204","sex":"Female","age_at_diagnosis":4.0,"age_at_death":null,"vital_status":"Alive","hospital":"VIC Hospital2","enrolment_date":1580515200000},{"patient_id":"P006301","sex":"Male","age_at_diagnosis":8.0,"age_at_death":9.0,"vital_status":"Dead","hospital":"NSW Hospital1","enrolment_date":1564617600000},{"patient_id":"P006304","sex":"Female","age_at_diagnosis":11.0,"age_at_death":null,"vital_status":"Alive","hospital":"VIC Hospital2","enrolment_date":1580515200000},{"patient_id":"P006404","sex":"Male","age_at_diagnosis":10.0,"age_at_death":null,"vital_status":"Alive","hospital":"VIC Hospital2","enrolment_date":1583020800000},{"patient_id":"P006501","sex":"Male","age_at_diagnosis":13.0,"age_at_death":14.0,"vital_status":"Dead","hospital":"NSW Hospital1","enrolment_date":1564617600000},{"patient_id":"P006502","sex":"Male","age_at_diagnosis":1.0,"age_at_death":null,"vital_status":"Alive","hospital":"NSW Hospital3","enrolment_date":1577836800000},{"patient_id":"P006904","sex":"Female","age_at_diagnosis":16.0,"age_at_death":null,"vital_status":"Alive","hospital":"VIC Hospital2","enrolment_date":1585699200000},{"patient_id":"P007104","sex":"Female","age_at_diagnosis":16.0,"age_at_death":null,"vital_status":"Alive","hospital":"VIC Hospital2","enrolment_date":1585699200000},{"patient_id":"T000101","sex":"Male","age_at_diagnosis":3.0,"age_at_death":4.0,"vital_status":"Dead","hospital":"NSW Hospital1","enrolment_date":1433116800000},{"patient_id":"T000601","sex":"Female","age_at_diagnosis":10.0,"age_at_death":18.0,"vital_status":"Dead","hospital":"NSW Hospital1","enrolment_date":1441065600000},{"patient_id":"T000801","sex":"Male","age_at_diagnosis":6.0,"age_at_death":9.0,"vital_status":"Dead","hospital":"NSW Hospital1","enrolment_date":1441065600000},{"patient_id":"T000901","sex":"Male","age_at_diagnosis":7.0,"age_at_death":null,"vital_status":"Alive","hospital":"NSW Hospital1","enrolment_date":1441065600000},{"patient_id":"T001101","sex":"Male","age_at_diagnosis":1.0,"age_at_death":2.0,"vital_status":"Dead","hospital":"NSW Hospital1","enrolment_date":1443657600000}]